taskng/__init__.py
taskng/_version_info.py
taskng/cli/__init__.py
taskng/cli/completion.py
taskng/cli/display.py
taskng/cli/error_handler.py
taskng/cli/main.py
taskng/cli/output.py
taskng/cli/commands/__init__.py
taskng/cli/commands/active.py
taskng/cli/commands/add.py
taskng/cli/commands/annotate.py
taskng/cli/commands/attach.py
taskng/cli/commands/board.py
taskng/cli/commands/calendar.py
taskng/cli/commands/config.py
taskng/cli/commands/context.py
taskng/cli/commands/delete.py
taskng/cli/commands/done.py
taskng/cli/commands/edit.py
taskng/cli/commands/export.py
taskng/cli/commands/import_cmd.py
taskng/cli/commands/init.py
taskng/cli/commands/list.py
taskng/cli/commands/modify.py
taskng/cli/commands/project_rename.py
taskng/cli/commands/projects.py
taskng/cli/commands/report.py
taskng/cli/commands/show.py
taskng/cli/commands/start.py
taskng/cli/commands/stats.py
taskng/cli/commands/stop.py
taskng/cli/commands/sync.py
taskng/cli/commands/tags.py
taskng/cli/commands/undo.py
taskng/config/__init__.py
taskng/config/defaults.py
taskng/config/settings.py
taskng/config/template.py
taskng/core/__init__.py
taskng/core/attachments.py
taskng/core/boards.py
taskng/core/context.py
taskng/core/dates.py
taskng/core/dependencies.py
taskng/core/exceptions.py
taskng/core/filters.py
taskng/core/hooks.py
taskng/core/id_parser.py
taskng/core/models.py
taskng/core/projects.py
taskng/core/recurrence.py
taskng/core/reports.py
taskng/core/sorting.py
taskng/core/statistics.py
taskng/core/uda.py
taskng/core/urgency.py
taskng/core/virtual_tags.py
taskng/storage/__init__.py
taskng/storage/database.py
taskng/storage/import_tw.py
taskng/storage/repository.py
taskng/storage/schema.py
taskng/storage/migrations/__init__.py
taskng/storage/migrations/env.py
taskng/storage/migrations/script.py.mako
taskng/storage/migrations/versions/001_initial_schema.py
taskng/storage/migrations/versions/002_add_attachments_table.py
taskng/storage/migrations/versions/__init__.py
taskng/sync/__init__.py
task_ng-0.1.6.dist-info/METADATA
task_ng-0.1.6.dist-info/WHEEL
task_ng-0.1.6.dist-info/entry_points.txt
task_ng-0.1.6.dist-info/licenses/LICENSE
task_ng-0.1.6.dist-info/RECORD
