Metadata-Version: 2.4
Name: task-ng
Version: 0.1.6
Summary: A modern Python reimagining of Taskwarrior
Project-URL: Homepage, https://github.com/yourusername/task-ng
Project-URL: Repository, https://github.com/yourusername/task-ng
Author: Task-NG Contributors
License: MIT
License-File: LICENSE
Classifier: Development Status :: 3 - Alpha
Classifier: Environment :: Console
Classifier: Intended Audience :: End Users/Desktop
Classifier: License :: OSI Approved :: MIT License
Classifier: Programming Language :: Python :: 3.11
Classifier: Programming Language :: Python :: 3.12
Classifier: Topic :: Office/Business :: Scheduling
Requires-Python: >=3.11
Requires-Dist: alembic>=1.12.0
Requires-Dist: dateparser>=1.1.0
Requires-Dist: pydantic>=2.0
Requires-Dist: python-dateutil>=2.8.0
Requires-Dist: python-magic>=0.4.27
Requires-Dist: pyyaml>=6.0
Requires-Dist: rich>=13.0
Requires-Dist: typer>=0.9.0
Provides-Extra: dev
Requires-Dist: mypy>=1.0; extra == 'dev'
Requires-Dist: pre-commit>=3.0; extra == 'dev'
Requires-Dist: pytest-cov>=4.0; extra == 'dev'
Requires-Dist: pytest>=7.0; extra == 'dev'
Requires-Dist: ruff>=0.1.0; extra == 'dev'
Requires-Dist: types-python-dateutil>=2.9.0; extra == 'dev'
Requires-Dist: types-pyyaml>=6.0.12; extra == 'dev'
